[
    [
        {
            "apellido": "Pascuan",
            "uuid": "d43e5499-71e0-47fe-b515-d190f5b81eb9",
            "nombre": "JoeLPrueba"
        },
        [
            {
                "tipo": "PLANTA",
                "vidaRestante": 95,
                "ataque": 60,
                "vidaCompleta": 95,
                "defensa": 44,
                "uuid": "9d3c8754-38b8-48bd-ae1f-0d42516102da",
                "nombre": "Arbok"
            },
            {
                "tipo": "ELECTRICO",
                "vidaRestante": 100,
                "ataque": 100,
                "vidaCompleta": 100,
                "defensa": 50,
                "uuid": "f4a34e45-d9e3-4d06-8400-38f49d32b366",
                "nombre": "Pikachu"
            },
            {
                "tipo": "FUEGO",
                "vidaRestante": 95,
                "ataque": 52,
                "vidaCompleta": 95,
                "defensa": 35,
                "uuid": "d8e79596-f18b-4e71-a80d-201401a5fdd7",
                "nombre": "Charmander"
            }
        ]
    ],
    [
        {
            "apellido": "Jimenez",
            "uuid": "7f5e3f3c-dece-49e0-a338-9f32d4e1d908",
            "nombre": "Valentina"
        },
        [
            {
                "tipo": "PLANTA",
                "vidaRestante": 95,
                "ataque": 60,
                "vidaCompleta": 95,
                "defensa": 44,
                "uuid": "9d3c8754-38b8-48bd-ae1f-0d42516102da",
                "nombre": "Arbok"
            },
            {
                "tipo": "ELECTRICO",
                "vidaRestante": 100,
                "ataque": 100,
                "vidaCompleta": 100,
                "defensa": 50,
                "uuid": "f4a34e45-d9e3-4d06-8400-38f49d32b366",
                "nombre": "Pikachu"
            },
            {
                "tipo": "FUEGO",
                "vidaRestante": 95,
                "ataque": 52,
                "vidaCompleta": 95,
                "defensa": 35,
                "uuid": "d8e79596-f18b-4e71-a80d-201401a5fdd7",
                "nombre": "Charmander"
            }
        ]
    ]
]